modelib/__init__.py
modelib/core/__init__.py
modelib/core/endpoint_factory.py
modelib/core/exceptions.py
modelib/core/schemas.py
modelib/runners/__init__.py
modelib/runners/base.py
modelib/runners/sklearn.py
modelib/server/__init__.py
modelib/server/app.py
modelib/server/infrastructure.py
modelib-0.3.1.dist-info/LICENSE
modelib-0.3.1.dist-info/METADATA
modelib-0.3.1.dist-info/WHEEL
modelib-0.3.1.dist-info/RECORD
