Metadata-Version: 2.1
Name: modelib
Version: 0.3.1
Summary: A minimalist framework for online deployment of sklearn-like models
Home-page: https://github.com/pier-digital/modelib
License: MIT
Keywords: machine learning,fastapi,sklearn,online deployment
Author: Gabriel Guarisa
Author-email: gabrielguarisa@gmail.com
Requires-Python: >=3.10,<4.0
Classifier: License :: OSI Approved :: MIT License
Classifier: Programming Language :: Python :: 3
Classifier: Programming Language :: Python :: 3.10
Classifier: Programming Language :: Python :: 3.11
Requires-Dist: fastapi
Requires-Dist: numpy
Requires-Dist: pandas (>=2.0,<3.0)
Requires-Dist: pydantic (>=2.0,<3.0)
Requires-Dist: python-slugify (>=8.0,<9.0)
Requires-Dist: scikit-learn
Project-URL: Repository, https://github.com/pier-digital/modelib
